{"nodes": [{"id": "next", "label": "next.ts", "file_type": "code", "source_file": "C:\\Users\\Rohith\\tradingview-mcp-jackson\\node_modules\\ajv\\lib\\vocabularies\\next.ts", "source_location": "L1"}], "edges": [{"source": "next", "target": "types", "relation": "imports_from", "confidence": "EXTRACTED", "source_file": "C:\\Users\\Rohith\\tradingview-mcp-jackson\\node_modules\\ajv\\lib\\vocabularies\\next.ts", "source_location": "L1", "weight": 1.0}, {"source": "next", "target": "dependentrequired", "relation": "imports_from", "confidence": "EXTRACTED", "source_file": "C:\\Users\\Rohith\\tradingview-mcp-jackson\\node_modules\\ajv\\lib\\vocabularies\\next.ts", "source_location": "L2", "weight": 1.0}, {"source": "next", "target": "dependentschemas", "relation": "imports_from", "confidence": "EXTRACTED", "source_file": "C:\\Users\\Rohith\\tradingview-mcp-jackson\\node_modules\\ajv\\lib\\vocabularies\\next.ts", "source_location": "L3", "weight": 1.0}, {"source": "next", "target": "limitcontains", "relation": "imports_from", "confidence": "EXTRACTED", "source_file": "C:\\Users\\Rohith\\tradingview-mcp-jackson\\node_modules\\ajv\\lib\\vocabularies\\next.ts", "source_location": "L4", "weight": 1.0}]}