{"nodes": [{"id": "v35", "label": "v35.js", "file_type": "code", "source_file": "C:\\Users\\Rohith\\tradingview-mcp-jackson\\node_modules\\uuid\\dist\\esm-node\\v35.js", "source_location": "L1"}, {"id": "v35_stringtobytes", "label": "stringToBytes()", "file_type": "code", "source_file": "C:\\Users\\Rohith\\tradingview-mcp-jackson\\node_modules\\uuid\\dist\\esm-node\\v35.js", "source_location": "L4"}, {"id": "v35_generateuuid", "label": "generateUUID()", "file_type": "code", "source_file": "C:\\Users\\Rohith\\tradingview-mcp-jackson\\node_modules\\uuid\\dist\\esm-node\\v35.js", "source_location": "L19"}], "edges": [{"source": "v35", "target": "stringify_js", "relation": "imports_from", "confidence": "EXTRACTED", "source_file": "C:\\Users\\Rohith\\tradingview-mcp-jackson\\node_modules\\uuid\\dist\\esm-node\\v35.js", "source_location": "L1", "weight": 1.0}, {"source": "v35", "target": "parse_js", "relation": "imports_from", "confidence": "EXTRACTED", "source_file": "C:\\Users\\Rohith\\tradingview-mcp-jackson\\node_modules\\uuid\\dist\\esm-node\\v35.js", "source_location": "L2", "weight": 1.0}, {"source": "v35", "target": "v35_stringtobytes", "relation": "contains", "confidence": "EXTRACTED", "source_file": "C:\\Users\\Rohith\\tradingview-mcp-jackson\\node_modules\\uuid\\dist\\esm-node\\v35.js", "source_location": "L4", "weight": 1.0}, {"source": "v35", "target": "v35_generateuuid", "relation": "contains", "confidence": "EXTRACTED", "source_file": "C:\\Users\\Rohith\\tradingview-mcp-jackson\\node_modules\\uuid\\dist\\esm-node\\v35.js", "source_location": "L19", "weight": 1.0}, {"source": "v35_generateuuid", "target": "v35_stringtobytes", "relation": "calls", "confidence": "EXTRACTED", "source_file": "C:\\Users\\Rohith\\tradingview-mcp-jackson\\node_modules\\uuid\\dist\\esm-node\\v35.js", "source_location": "L21", "weight": 1.0}]}