{"nodes": [{"id": "index", "label": "index.js", "file_type": "code", "source_file": "C:\\Users\\Rohith\\tradingview-mcp-jackson\\node_modules\\hono\\dist\\cjs\\middleware\\logger\\index.js", "source_location": "L1"}, {"id": "index_humanize", "label": "humanize()", "file_type": "code", "source_file": "C:\\Users\\Rohith\\tradingview-mcp-jackson\\node_modules\\hono\\dist\\cjs\\middleware\\logger\\index.js", "source_location": "L30"}, {"id": "index_time", "label": "time()", "file_type": "code", "source_file": "C:\\Users\\Rohith\\tradingview-mcp-jackson\\node_modules\\hono\\dist\\cjs\\middleware\\logger\\index.js", "source_location": "L35"}, {"id": "index_colorstatus", "label": "colorStatus()", "file_type": "code", "source_file": "C:\\Users\\Rohith\\tradingview-mcp-jackson\\node_modules\\hono\\dist\\cjs\\middleware\\logger\\index.js", "source_location": "L39"}, {"id": "index_log", "label": "log()", "file_type": "code", "source_file": "C:\\Users\\Rohith\\tradingview-mcp-jackson\\node_modules\\hono\\dist\\cjs\\middleware\\logger\\index.js", "source_location": "L55"}, {"id": "index_logger", "label": "logger()", "file_type": "code", "source_file": "C:\\Users\\Rohith\\tradingview-mcp-jackson\\node_modules\\hono\\dist\\cjs\\middleware\\logger\\index.js", "source_location": "L59"}], "edges": [{"source": "index", "target": "index_humanize", "relation": "contains", "confidence": "EXTRACTED", "source_file": "C:\\Users\\Rohith\\tradingview-mcp-jackson\\node_modules\\hono\\dist\\cjs\\middleware\\logger\\index.js", "source_location": "L30", "weight": 1.0}, {"source": "index", "target": "index_time", "relation": "contains", "confidence": "EXTRACTED", "source_file": "C:\\Users\\Rohith\\tradingview-mcp-jackson\\node_modules\\hono\\dist\\cjs\\middleware\\logger\\index.js", "source_location": "L35", "weight": 1.0}, {"source": "index", "target": "index_colorstatus", "relation": "contains", "confidence": "EXTRACTED", "source_file": "C:\\Users\\Rohith\\tradingview-mcp-jackson\\node_modules\\hono\\dist\\cjs\\middleware\\logger\\index.js", "source_location": "L39", "weight": 1.0}, {"source": "index", "target": "index_log", "relation": "contains", "confidence": "EXTRACTED", "source_file": "C:\\Users\\Rohith\\tradingview-mcp-jackson\\node_modules\\hono\\dist\\cjs\\middleware\\logger\\index.js", "source_location": "L55", "weight": 1.0}, {"source": "index", "target": "index_logger", "relation": "contains", "confidence": "EXTRACTED", "source_file": "C:\\Users\\Rohith\\tradingview-mcp-jackson\\node_modules\\hono\\dist\\cjs\\middleware\\logger\\index.js", "source_location": "L59", "weight": 1.0}, {"source": "index_time", "target": "index_humanize", "relation": "calls", "confidence": "EXTRACTED", "source_file": "C:\\Users\\Rohith\\tradingview-mcp-jackson\\node_modules\\hono\\dist\\cjs\\middleware\\logger\\index.js", "source_location": "L37", "weight": 1.0}, {"source": "index_log", "target": "index_colorstatus", "relation": "calls", "confidence": "EXTRACTED", "source_file": "C:\\Users\\Rohith\\tradingview-mcp-jackson\\node_modules\\hono\\dist\\cjs\\middleware\\logger\\index.js", "source_location": "L56", "weight": 1.0}, {"source": "index_logger", "target": "index_log", "relation": "calls", "confidence": "EXTRACTED", "source_file": "C:\\Users\\Rohith\\tradingview-mcp-jackson\\node_modules\\hono\\dist\\cjs\\middleware\\logger\\index.js", "source_location": "L63", "weight": 1.0}, {"source": "index_logger", "target": "index_time", "relation": "calls", "confidence": "EXTRACTED", "source_file": "C:\\Users\\Rohith\\tradingview-mcp-jackson\\node_modules\\hono\\dist\\cjs\\middleware\\logger\\index.js", "source_location": "L66", "weight": 1.0}]}