{"nodes": [{"id": "auto_filter_xform", "label": "auto-filter-xform.js", "file_type": "code", "source_file": "C:\\Users\\Rohith\\tradingview-mcp-jackson\\node_modules\\exceljs\\lib\\xlsx\\xform\\table\\auto-filter-xform.js", "source_location": "L1"}, {"id": "auto_filter_xform_autofilterxform", "label": "AutoFilterXform", "file_type": "code", "source_file": "C:\\Users\\Rohith\\tradingview-mcp-jackson\\node_modules\\exceljs\\lib\\xlsx\\xform\\table\\auto-filter-xform.js", "source_location": "L5"}, {"id": "auto_filter_xform_autofilterxform_constructor", "label": ".constructor()", "file_type": "code", "source_file": "C:\\Users\\Rohith\\tradingview-mcp-jackson\\node_modules\\exceljs\\lib\\xlsx\\xform\\table\\auto-filter-xform.js", "source_location": "L6"}, {"id": "auto_filter_xform_autofilterxform_tag", "label": ".tag()", "file_type": "code", "source_file": "C:\\Users\\Rohith\\tradingview-mcp-jackson\\node_modules\\exceljs\\lib\\xlsx\\xform\\table\\auto-filter-xform.js", "source_location": "L14"}, {"id": "auto_filter_xform_autofilterxform_prepare", "label": ".prepare()", "file_type": "code", "source_file": "C:\\Users\\Rohith\\tradingview-mcp-jackson\\node_modules\\exceljs\\lib\\xlsx\\xform\\table\\auto-filter-xform.js", "source_location": "L18"}, {"id": "auto_filter_xform_autofilterxform_render", "label": ".render()", "file_type": "code", "source_file": "C:\\Users\\Rohith\\tradingview-mcp-jackson\\node_modules\\exceljs\\lib\\xlsx\\xform\\table\\auto-filter-xform.js", "source_location": "L24"}, {"id": "auto_filter_xform_autofilterxform_parseopen", "label": ".parseOpen()", "file_type": "code", "source_file": "C:\\Users\\Rohith\\tradingview-mcp-jackson\\node_modules\\exceljs\\lib\\xlsx\\xform\\table\\auto-filter-xform.js", "source_location": "L35"}, {"id": "auto_filter_xform_autofilterxform_parsetext", "label": ".parseText()", "file_type": "code", "source_file": "C:\\Users\\Rohith\\tradingview-mcp-jackson\\node_modules\\exceljs\\lib\\xlsx\\xform\\table\\auto-filter-xform.js", "source_location": "L58"}, {"id": "auto_filter_xform_autofilterxform_parseclose", "label": ".parseClose()", "file_type": "code", "source_file": "C:\\Users\\Rohith\\tradingview-mcp-jackson\\node_modules\\exceljs\\lib\\xlsx\\xform\\table\\auto-filter-xform.js", "source_location": "L64"}], "edges": [{"source": "auto_filter_xform", "target": "auto_filter_xform_autofilterxform", "relation": "contains", "confidence": "EXTRACTED", "source_file": "C:\\Users\\Rohith\\tradingview-mcp-jackson\\node_modules\\exceljs\\lib\\xlsx\\xform\\table\\auto-filter-xform.js", "source_location": "L5", "weight": 1.0}, {"source": "auto_filter_xform_autofilterxform", "target": "auto_filter_xform_autofilterxform_constructor", "relation": "method", "confidence": "EXTRACTED", "source_file": "C:\\Users\\Rohith\\tradingview-mcp-jackson\\node_modules\\exceljs\\lib\\xlsx\\xform\\table\\auto-filter-xform.js", "source_location": "L6", "weight": 1.0}, {"source": "auto_filter_xform_autofilterxform", "target": "auto_filter_xform_autofilterxform_tag", "relation": "method", "confidence": "EXTRACTED", "source_file": "C:\\Users\\Rohith\\tradingview-mcp-jackson\\node_modules\\exceljs\\lib\\xlsx\\xform\\table\\auto-filter-xform.js", "source_location": "L14", "weight": 1.0}, {"source": "auto_filter_xform_autofilterxform", "target": "auto_filter_xform_autofilterxform_prepare", "relation": "method", "confidence": "EXTRACTED", "source_file": "C:\\Users\\Rohith\\tradingview-mcp-jackson\\node_modules\\exceljs\\lib\\xlsx\\xform\\table\\auto-filter-xform.js", "source_location": "L18", "weight": 1.0}, {"source": "auto_filter_xform_autofilterxform", "target": "auto_filter_xform_autofilterxform_render", "relation": "method", "confidence": "EXTRACTED", "source_file": "C:\\Users\\Rohith\\tradingview-mcp-jackson\\node_modules\\exceljs\\lib\\xlsx\\xform\\table\\auto-filter-xform.js", "source_location": "L24", "weight": 1.0}, {"source": "auto_filter_xform_autofilterxform", "target": "auto_filter_xform_autofilterxform_parseopen", "relation": "method", "confidence": "EXTRACTED", "source_file": "C:\\Users\\Rohith\\tradingview-mcp-jackson\\node_modules\\exceljs\\lib\\xlsx\\xform\\table\\auto-filter-xform.js", "source_location": "L35", "weight": 1.0}, {"source": "auto_filter_xform_autofilterxform", "target": "auto_filter_xform_autofilterxform_parsetext", "relation": "method", "confidence": "EXTRACTED", "source_file": "C:\\Users\\Rohith\\tradingview-mcp-jackson\\node_modules\\exceljs\\lib\\xlsx\\xform\\table\\auto-filter-xform.js", "source_location": "L58", "weight": 1.0}, {"source": "auto_filter_xform_autofilterxform", "target": "auto_filter_xform_autofilterxform_parseclose", "relation": "method", "confidence": "EXTRACTED", "source_file": "C:\\Users\\Rohith\\tradingview-mcp-jackson\\node_modules\\exceljs\\lib\\xlsx\\xform\\table\\auto-filter-xform.js", "source_location": "L64", "weight": 1.0}]}